{
	"configurations" : 
	[
		{
			"directories" : 
			[
				{
					"build" : ".",
					"minimumCMakeVersion" : 
					{
						"string" : "2.8"
					},
					"projectIndex" : 0,
					"source" : ".",
					"targetIndexes" : 
					[
						0
					]
				}
			],
			"name" : "Debug",
			"projects" : 
			[
				{
					"directoryIndexes" : 
					[
						0
					],
					"name" : "graph_search",
					"targetIndexes" : 
					[
						0
					]
				}
			],
			"targets" : 
			[
				{
					"directoryIndex" : 0,
					"id" : "graph_search::@6890427a1f51a3e7e1df",
					"jsonFile" : "target-graph_search-Debug-6ae182140621e0f62049.json",
					"name" : "graph_search",
					"projectIndex" : 0
				}
			]
		}
	],
	"kind" : "codemodel",
	"paths" : 
	{
		"build" : "/home/esteban/git/pfms-2020a-esteban-andrade/scratch/week05/starter/graph_search/build",
		"source" : "/home/esteban/git/pfms-2020a-esteban-andrade/scratch/week05/starter/graph_search"
	},
	"version" : 
	{
		"major" : 2,
		"minor" : 0
	}
}
